memalot/__init__.py
memalot/api.py
memalot/base.py
memalot/cli.py
memalot/interface.py
memalot/memory.py
memalot/monitors.py
memalot/networkx_copy.py
memalot/objects.py
memalot/options.py
memalot/output.py
memalot/report_generator.py
memalot/reports.py
memalot/snapshots.py
memalot/themes.py
memalot/utils.py
memalot/mcp_server/__init__.py
memalot/mcp_server/main.py
memalot-2.0.1.dist-info/licenses/LICENSE
tests/__init__.py
tests/test_api.py
tests/test_base.py
tests/test_cli.py
tests/test_memory.py
tests/test_monitors.py
tests/test_objects.py
tests/test_options.py
tests/test_output.py
tests/test_report_generator.py
tests/test_reports.py
tests/test_snapshots.py
tests/test_utils.py
tests/utils_for_testing.py
tests/mcp_server/__init__.py
tests/mcp_server/test_main.py
tests_integration/__init__.py
tests_integration/test_cache_examples.py
tests_integration/test_converging_tree.py
tests_integration/test_integration.py
tests_integration/test_time_based.py
tests_integration/utils.py
tests_performance/__init__.py
tests_performance/test_performance_barbell.py
tests_performance/test_performance_objects.py
memalot-2.0.1.dist-info/METADATA
memalot-2.0.1.dist-info/WHEEL
memalot-2.0.1.dist-info/entry_points.txt
memalot-2.0.1.dist-info/top_level.txt
memalot-2.0.1.dist-info/RECORD
